strixhoot/__init__.py
strixhoot/cgan.py
strixhoot/cli.py
strixhoot/cvae.py
strixhoot/data_preprocessor.py
strixhoot/lgbm_regressor.py
strixhoot/lgbm_tuner.py
strixhoot/trainer.py
strixhoot/utils.py
strixhoot-0.0.9.dist-info/LICENSE
strixhoot-0.0.9.dist-info/METADATA
strixhoot-0.0.9.dist-info/WHEEL
strixhoot-0.0.9.dist-info/entry_points.txt
strixhoot-0.0.9.dist-info/top_level.txt
strixhoot-0.0.9.dist-info/RECORD
