Metadata-Version: 2.1
Name: strixhoot
Version: 0.0.9
Summary: Hybrid VAE-GAN with LightGBM for class-imbalanced regression task
Home-page: https://github.com/AliBavarchee/strixhoot
Author: Ali Bavarchee
Author-email: ali.bavarchee@gmail.com
License: MIT
Keywords: machine-learning,deep-learning,data-augmentation,class-imbalance,vae,gan,lightgbm
Classifier: Programming Language :: Python :: 3
Classifier: License :: OSI Approved :: MIT License
Classifier: Operating System :: OS Independent
Classifier: Intended Audience :: Science/Research
Classifier: Topic :: Scientific/Engineering :: Artificial Intelligence
Requires-Python: >=3.8
License-File: LICENSE
Requires-Dist: dill >=0.3.9
Requires-Dist: dask >=2024.10.0
Requires-Dist: numpy >=1.21.0
Requires-Dist: pandas >=1.3.0
Requires-Dist: umap >=0.1.1
Requires-Dist: imblearn >=0.0
Requires-Dist: imbalanced-learn >=0.13.0
Requires-Dist: lightgbm >=4.5.0
Requires-Dist: tensorflow >=2.8.0
Requires-Dist: keras >=3.8.0
Requires-Dist: scikit-learn >=1.0.0
Requires-Dist: lightgbm >=3.3.0
Requires-Dist: scipy >=1.7.0
Requires-Dist: matplotlib >=3.5.0
Requires-Dist: seaborn >=0.11.0
Requires-Dist: joblib >=1.1.0
Requires-Dist: tqdm >=4.64.0
